google/cloud/dialogflow/__init__.py
google/cloud/dialogflow/gapic_version.py
google/cloud/dialogflow/py.typed
google/cloud/dialogflow_v2/__init__.py
google/cloud/dialogflow_v2/gapic_metadata.json
google/cloud/dialogflow_v2/gapic_version.py
google/cloud/dialogflow_v2/py.typed
google/cloud/dialogflow_v2/services/__init__.py
google/cloud/dialogflow_v2/services/agents/__init__.py
google/cloud/dialogflow_v2/services/agents/async_client.py
google/cloud/dialogflow_v2/services/agents/client.py
google/cloud/dialogflow_v2/services/agents/pagers.py
google/cloud/dialogflow_v2/services/agents/transports/__init__.py
google/cloud/dialogflow_v2/services/agents/transports/base.py
google/cloud/dialogflow_v2/services/agents/transports/grpc.py
google/cloud/dialogflow_v2/services/agents/transports/grpc_asyncio.py
google/cloud/dialogflow_v2/services/agents/transports/rest.py
google/cloud/dialogflow_v2/services/agents/transports/rest_base.py
google/cloud/dialogflow_v2/services/answer_records/__init__.py
google/cloud/dialogflow_v2/services/answer_records/async_client.py
google/cloud/dialogflow_v2/services/answer_records/client.py
google/cloud/dialogflow_v2/services/answer_records/pagers.py
google/cloud/dialogflow_v2/services/answer_records/transports/__init__.py
google/cloud/dialogflow_v2/services/answer_records/transports/base.py
google/cloud/dialogflow_v2/services/answer_records/transports/grpc.py
google/cloud/dialogflow_v2/services/answer_records/transports/grpc_asyncio.py
google/cloud/dialogflow_v2/services/answer_records/transports/rest.py
google/cloud/dialogflow_v2/services/answer_records/transports/rest_base.py
google/cloud/dialogflow_v2/services/contexts/__init__.py
google/cloud/dialogflow_v2/services/contexts/async_client.py
google/cloud/dialogflow_v2/services/contexts/client.py
google/cloud/dialogflow_v2/services/contexts/pagers.py
google/cloud/dialogflow_v2/services/contexts/transports/__init__.py
google/cloud/dialogflow_v2/services/contexts/transports/base.py
google_cloud_dialogflow-2.44.0.dist-info/licenses/LICENSE
google_cloud_dialogflow-2.44.0.dist-info/METADATA
google_cloud_dialogflow-2.44.0.dist-info/WHEEL
google_cloud_dialogflow-2.44.0.dist-info/top_level.txt
google_cloud_dialogflow-2.44.0.dist-info/RECORD
